azure/__init__.py
azure/cli/__init__.py
azure/cli/__main__.py
opal_azure_cli-2.0.70.data/scripts/az
opal_azure_cli-2.0.70.data/scripts/az.bat
opal_azure_cli-2.0.70.data/scripts/az.completion.sh
opal_azure_cli-2.0.70.dist-info/LICENSE.txt
opal_azure_cli-2.0.70.dist-info/METADATA
opal_azure_cli-2.0.70.dist-info/WHEEL
opal_azure_cli-2.0.70.dist-info/top_level.txt
opal_azure_cli-2.0.70.dist-info/RECORD
