Metadata-Version: 2.1
Name: opal-azure-cli
Version: 2.0.70
Summary: Microsoft Azure Command-Line Tools
Home-page: https://github.com/Azure/azure-cli
Author: Microsoft Corporation
Author-email: azpycli@microsoft.com
License: MIT
Platform: UNKNOWN
Classifier: Development Status :: 5 - Production/Stable
Classifier: Intended Audience :: Developers
Classifier: Intended Audience :: System Administrators
Classifier: Programming Language :: Python
Classifier: Programming Language :: Python :: 2
Classifier: Programming Language :: Python :: 2.7
Classifier: Programming Language :: Python :: 3
Classifier: Programming Language :: Python :: 3.4
Classifier: Programming Language :: Python :: 3.5
Classifier: Programming Language :: Python :: 3.6
Classifier: License :: OSI Approved :: MIT License
Requires-Dist: opal-azure-cli-acr
Requires-Dist: opal-azure-cli-acs
Requires-Dist: opal-azure-cli-advisor
Requires-Dist: opal-azure-cli-ams
Requires-Dist: opal-azure-cli-appservice
Requires-Dist: opal-azure-cli-backup
Requires-Dist: opal-azure-cli-batch
Requires-Dist: opal-azure-cli-batchai
Requires-Dist: opal-azure-cli-billing
Requires-Dist: opal-azure-cli-botservice
Requires-Dist: opal-azure-cli-cdn
Requires-Dist: opal-azure-cli-cloud
Requires-Dist: opal-azure-cli-cognitiveservices
Requires-Dist: opal-azure-cli-command-modules-nspkg
Requires-Dist: opal-azure-cli-configure
Requires-Dist: opal-azure-cli-consumption
Requires-Dist: opal-azure-cli-container
Requires-Dist: opal-azure-cli-core
Requires-Dist: opal-azure-cli-cosmosdb
Requires-Dist: opal-azure-cli-deploymentmanager
Requires-Dist: opal-azure-cli-dla
Requires-Dist: opal-azure-cli-dls
Requires-Dist: opal-azure-cli-dms
Requires-Dist: opal-azure-cli-eventgrid
Requires-Dist: opal-azure-cli-eventhubs
Requires-Dist: opal-azure-cli-extension
Requires-Dist: opal-azure-cli-feedback
Requires-Dist: opal-azure-cli-find
Requires-Dist: opal-azure-cli-hdinsight
Requires-Dist: opal-azure-cli-interactive
Requires-Dist: opal-azure-cli-iot
Requires-Dist: opal-azure-cli-iotcentral
Requires-Dist: opal-azure-cli-keyvault
Requires-Dist: opal-azure-cli-kusto
Requires-Dist: opal-azure-cli-lab
Requires-Dist: opal-azure-cli-maps
Requires-Dist: opal-azure-cli-monitor
Requires-Dist: opal-azure-cli-natgateway
Requires-Dist: opal-azure-cli-network
Requires-Dist: opal-azure-cli-nspkg
Requires-Dist: opal-azure-cli-policyinsights
Requires-Dist: opal-azure-cli-privatedns
Requires-Dist: opal-azure-cli-profile
Requires-Dist: opal-azure-cli-rdbms
Requires-Dist: opal-azure-cli-redis
Requires-Dist: opal-azure-cli-relay
Requires-Dist: opal-azure-cli-reservations
Requires-Dist: opal-azure-cli-resource
Requires-Dist: opal-azure-cli-role
Requires-Dist: opal-azure-cli-search
Requires-Dist: opal-azure-cli-security
Requires-Dist: opal-azure-cli-servicebus
Requires-Dist: opal-azure-cli-servicefabric
Requires-Dist: opal-azure-cli-signalr
Requires-Dist: opal-azure-cli-sql
Requires-Dist: opal-azure-cli-sqlvm
Requires-Dist: opal-azure-cli-storage
Requires-Dist: opal-azure-cli-telemetry
Requires-Dist: opal-azure-cli-vm
Requires-Dist: azure-cli-nspkg (>=2.0.0)
